Workbook

Sheet Leia-me
A1: Clube.org — Modelo Financeiro (Praça-piloto: Curitiba)
A3: Como usar este arquivo
A5: - Células em AZUL sobre fundo AMARELO são premissas editáveis (inputs). Todo o resto é fórmula — muda automaticamente.
A6: - Aba 'Premissas': parâmetros de ticket, mix de planos, custos (% de receita) e ritmo de aquisição/churn.
A7: - Aba 'Projeção 24 Meses': P&L mensal derivado 100% das premissas (assinantes, receita, custos, EBITDA).
A8: - Aba 'Unit Economics': CAC, LTV, payback e ponto de equilíbrio, calculados a partir das mesmas premissas.
A9: - Aba 'Investimento Inicial': capex e capital de giro pré-operacional, com fontes/observações por linha.
A10: - Aba 'Comparativo de Capitais': matriz de decisão com pesos ajustáveis para a escolha da praça-piloto e ordem de expansão.
A12: Os valores de mercado (renda per capita, população, produtores certificados) vêm de pesquisa pública
A13: (IBGE/PNAD Contínua 2025, MAPA/CNPO, Organis, IMARC Group) — ver PLANO_DE_NEGOCIOS.md, seção 2.5, para as fontes completas.
A14: Os parâmetros operacionais (ticket, churn, CAC, custos) são estimativas de dimensionamento inicial, com faixas de mercado do setor de
A15: assinatura de alimentos frescos — ajuste-os conforme dados reais do piloto forem chegando (ver seção 11 do plano de negócios).

Sheet Premissas
A1: Premissas do Modelo — Praça-piloto
A3: Planos e Ticket
A4: Plano | B4: Ticket semanal (R$) | C4: Mix (%)
A5: Solo | B5: 79 | C5: 0.35
A6: Família | B6: 134 | C6: 0.45
A7: Família + | B7: 184 | C7: 0.2
A8: Soma do mix (deve ser 100%) | C8: =SUM(C5:C7) -> 1
A10: Ticket médio ponderado / semana (R$) | B10: =SUMPRODUCT(B5:B7,C5:C7) -> 124.75
A11: Semanas por mês (média) | B11: 4.33
A12: Ticket médio ponderado / mês (R$) | B12: =B10*B11 -> 540.1675
A14: Estrutura de Custo (% da receita)
A15: Custo de produto (pagamento a fornecedores) | B15: 0.44 | D15: Ponto médio da faixa 40-48% (seção 11.2 do plano)
A16: Operação do CD (equipe, embalagem, energia) | B16: 0.14 | D16: Ponto médio da faixa 12-16%
A17: Logística / última milha | B17: 0.12 | D17: Ponto médio da faixa 10-15%
A18: Tecnologia (plataformas, manutenção) | B18: 0.045 | D18: Ponto médio da faixa 3-6%
A19: Administrativo / geral | B19: 0.065 | D19: Ponto médio da faixa 5-8%
A21: Aquisição, Churn e Ramp de Assinantes
A22: Assinantes ativos no Mês 1 (início do piloto) | B22: 50
A23: Novos assinantes brutos / mês (Meses 1-6) | B23: 60
A24: Novos assinantes brutos / mês (Meses 7-24) | B24: 110
A25: Churn mensal (%) | B25: 0.09
A26: CAC médio por novo assinante (R$) | B26: 140

Sheet Projecao 24 Meses
A1: Projeção Financeira 24 Meses — Praça-piloto (Curitiba)
A2: Todas as células desta aba são fórmulas derivadas da aba Premissas — não há números digitados aqui.
A4: Mês | B4: Assinantes início | C4: Novos assinantes | D4: Cancelamentos (churn) | E4: Assinantes fim | F4: Receita | G4: Custo produto | H4: Custo CD | I4: Logística | J4: Marketing (CAC) | K4: Tecnologia | L4: Admin | M4: Total custos | N4: EBITDA | O4: Margem EBITDA | P4: EBITDA Acumulado
A5: 1 | B5: =Premissas!$B$22 -> 50 | C5: =IF(A5<=6,Premissas!$B$23,Premissas!$B$24) -> 60 | D5: =B5*Premissas!$B$25 -> 4.5 | E5: =B5+C5-D5 -> 105.5 | F5: =E5*Premissas!$B$12 -> 56987.671 | G5: =$F5*Premissas!$B$15 -> 25074.575 | H5: =$F5*Premissas!$B$16 -> 7978.274 | I5: =$F5*Premissas!$B$17 -> 6838.5206 | J5: =C5*Premissas!$B$26 -> 8400 | K5: =$F5*Premissas!$B$18 -> 2564.4452 | L5: =$F5*Premissas!$B$19 -> 3704.1986 | M5: =SUM(G5:L5) -> 54560.014 | N5: =F5-M5 -> 2427.6575 | O5: =IFERROR(N5/F5,0) -> 0.042599697 | P5: =N5 -> 2427.6575
A6: 2 | B6: =E5 -> 105.5 | C6: =IF(A6<=6,Premissas!$B$23,Premissas!$B$24) -> 60 | D6: =B6*Premissas!$B$25 -> 9.495 | E6: =B6+C6-D6 -> 156.005 | F6: =E6*Premissas!$B$12 -> 84268.831 | G6: =$F6*Premissas!$B$15 -> 37078.286 | H6: =$F6*Premissas!$B$16 -> 11797.636 | I6: =$F6*Premissas!$B$17 -> 10112.26 | J6: =C6*Premissas!$B$26 -> 8400 | K6: =$F6*Premissas!$B$18 -> 3792.0974 | L6: =$F6*Premissas!$B$19 -> 5477.474 | M6: =SUM(G6:L6) -> 76657.753 | N6: =F6-M6 -> 7611.0779 | O6: =IFERROR(N6/F6,0) -> 0.090319016 | P6: =P5+N6 -> 10038.735
A7: 3 | B7: =E6 -> 156.005 | C7: =IF(A7<=6,Premissas!$B$23,Premissas!$B$24) -> 60 | D7: =B7*Premissas!$B$25 -> 14.04045 | E7: =B7+C7-D7 -> 201.96455 | F7: =E7*Premissas!$B$12 -> 109094.69 | G7: =$F7*Premissas!$B$15 -> 48001.662 | H7: =$F7*Premissas!$B$16 -> 15273.256 | I7: =$F7*Premissas!$B$17 -> 13091.362 | J7: =C7*Premissas!$B$26 -> 8400 | K7: =$F7*Premissas!$B$18 -> 4909.2609 | L7: =$F7*Premissas!$B$19 -> 7091.1546 | M7: =SUM(G7:L7) -> 96766.696 | N7: =F7-M7 -> 12327.99 | O7: =IFERROR(N7/F7,0) -> 0.11300267 | P7: =P6+N7 -> 22366.726
A8: 4 | B8: =E7 -> 201.96455 | C8: =IF(A8<=6,Premissas!$B$23,Premissas!$B$24) -> 60 | D8: =B8*Premissas!$B$25 -> 18.17681 | E8: =B8+C8-D8 -> 243.78774 | F8: =E8*Premissas!$B$12 -> 131686.21 | G8: =$F8*Premissas!$B$15 -> 57941.934 | H8: =$F8*Premissas!$B$16 -> 18436.07 | I8: =$F8*Premissas!$B$17 -> 15802.346 | J8: =C8*Premissas!$B$26 -> 8400 | K8: =$F8*Premissas!$B$18 -> 5925.8796 | L8: =$F8*Premissas!$B$19 -> 8559.6039 | M8: =SUM(G8:L8) -> 115065.83 | N8: =F8-M8 -> 16620.381 | O8: =IFERROR(N8/F8,0) -> 0.126212 | P8: =P7+N8 -> 38987.106
A9: 5 | B9: =E8 -> 243.78774 | C9: =IF(A9<=6,Premissas!$B$23,Premissas!$B$24) -> 60 | D9: =B9*Premissas!$B$25 -> 21.940897 | E9: =B9+C9-D9 -> 281.84684 | F9: =E9*Premissas!$B$12 -> 152244.51 | G9: =$F9*Premissas!$B$15 -> 66987.582 | H9: =$F9*Premissas!$B$16 -> 21314.231 | I9: =$F9*Premissas!$B$17 -> 18269.341 | J9: =C9*Premissas!$B$26 -> 8400 | K9: =$F9*Premissas!$B$18 -> 6851.0027 | L9: =$F9*Premissas!$B$19 -> 9895.8928 | M9: =SUM(G9:L9) -> 131718.05 | N9: =F9-M9 -> 20526.456 | O9: =IFERROR(N9/F9,0) -> 0.13482559 | P9: =P8+N9 -> 59513.562
A10: 6 | B10: =E9 -> 281.84684 | C10: =IF(A10<=6,Premissas!$B$23,Premissas!$B$24) -> 60 | D10: =B10*Premissas!$B$25 -> 25.366216 | E10: =B10+C10-D10 -> 316.48063 | F10: =E10*Premissas!$B$12 -> 170952.55 | G10: =$F10*Premissas!$B$15 -> 75219.122 | H10: =$F10*Premissas!$B$16 -> 23933.357 | I10: =$F10*Premissas!$B$17 -> 20514.306 | J10: =C10*Premissas!$B$26 -> 8400 | K10: =$F10*Premissas!$B$18 -> 7692.8647 | L10: =$F10*Premissas!$B$19 -> 11111.916 | M10: =SUM(G10:L10) -> 146871.57 | N10: =F10-M10 -> 24080.984 | O10: =IFERROR(N10/F10,0) -> 0.14086356 | P10: =P9+N10 -> 83594.547
A11: 7 | B11: =E10 -> 316.48063 | C11: =IF(A11<=6,Premissas!$B$23,Premissas!$B$24) -> 110 | D11: =B11*Premissas!$B$25 -> 28.483257 | E11: =B11+C11-D11 -> 397.99737 | F11: =E11*Premissas!$B$12 -> 214985.25 | G11: =$F11*Premissas!$B$15 -> 94593.508 | H11: =$F11*Premissas!$B$16 -> 30097.934 | I11: =$F11*Premissas!$B$17 -> 25798.229 | J11: =C11*Premissas!$B$26 -> 15400 | K11: =$F11*Premissas!$B$18 -> 9674.336 | L11: =$F11*Premissas!$B$19 -> 13974.041 | M11: =SUM(G11:L11) -> 189538.05 | N11: =F11-M11 -> 25447.197 | O11: =IFERROR(N11/F11,0) -> 0.11836718 | P11: =P10+N11 -> 109041.74
A12: 8 | B12: =E11 -> 397.99737 | C12: =IF(A12<=6,Premissas!$B$23,Premissas!$B$24) -> 110 | D12: =B12*Premissas!$B$25 -> 35.819763 | E12: =B12+C12-D12 -> 472.17761 | F12: =E12*Premissas!$B$12 -> 255055 | G12: =$F12*Premissas!$B$15 -> 112224.2 | H12: =$F12*Premissas!$B$16 -> 35707.7 | I12: =$F12*Premissas!$B$17 -> 30606.6 | J12: =C12*Premissas!$B$26 -> 15400 | K12: =$F12*Premissas!$B$18 -> 11477.475 | L12: =$F12*Premissas!$B$19 -> 16578.575 | M12: =SUM(G12:L12) -> 221994.55 | N12: =F12-M12 -> 33060.45 | O12: =IFERROR(N12/F12,0) -> 0.12962087 | P12: =P11+N12 -> 142102.19
A13: 9 | B13: =E12 -> 472.17761 | C13: =IF(A13<=6,Premissas!$B$23,Premissas!$B$24) -> 110 | D13: =B13*Premissas!$B$25 -> 42.495985 | E13: =B13+C13-D13 -> 539.68162 | F13: =E13*Premissas!$B$12 -> 291518.47 | G13: =$F13*Premissas!$B$15 -> 128268.13 | H13: =$F13*Premissas!$B$16 -> 40812.586 | I13: =$F13*Premissas!$B$17 -> 34982.217 | J13: =C13*Premissas!$B$26 -> 15400 | K13: =$F13*Premissas!$B$18 -> 13118.331 | L13: =$F13*Premissas!$B$19 -> 18948.701 | M13: =SUM(G13:L13) -> 251529.96 | N13: =F13-M13 -> 39988.51 | O13: =IFERROR(N13/F13,0) -> 0.13717316 | P13: =P12+N13 -> 182090.7
A14: 10 | B14: =E13 -> 539.68162 | C14: =IF(A14<=6,Premissas!$B$23,Premissas!$B$24) -> 110 | D14: =B14*Premissas!$B$25 -> 48.571346 | E14: =B14+C14-D14 -> 601.11028 | F14: =E14*Premissas!$B$12 -> 324700.24 | G14: =$F14*Premissas!$B$15 -> 142868.1 | H14: =$F14*Premissas!$B$16 -> 45458.033 | I14: =$F14*Premissas!$B$17 -> 38964.028 | J14: =C14*Premissas!$B$26 -> 15400 | K14: =$F14*Premissas!$B$18 -> 14611.511 | L14: =$F14*Premissas!$B$19 -> 21105.515 | M14: =SUM(G14:L14) -> 278407.19 | N14: =F14-M14 -> 46293.045 | O14: =IFERROR(N14/F14,0) -> 0.14257164 | P14: =P13+N14 -> 228383.75
A15: 11 | B15: =E14 -> 601.11028 | C15: =IF(A15<=6,Premissas!$B$23,Premissas!$B$24) -> 110 | D15: =B15*Premissas!$B$25 -> 54.099925 | E15: =B15+C15-D15 -> 657.01035 | F15: =E15*Premissas!$B$12 -> 354895.64 | G15: =$F15*Premissas!$B$15 -> 156154.08 | H15: =$F15*Premissas!$B$16 -> 49685.39 | I15: =$F15*Premissas!$B$17 -> 42587.477 | J15: =C15*Premissas!$B$26 -> 15400 | K15: =$F15*Premissas!$B$18 -> 15970.304 | L15: =$F15*Premissas!$B$19 -> 23068.217 | M15: =SUM(G15:L15) -> 302865.47 | N15: =F15-M15 -> 52030.171 | O15: =IFERROR(N15/F15,0) -> 0.14660696 | P15: =P14+N15 -> 280413.92
A16: 12 | B16: =E15 -> 657.01035 | C16: =IF(A16<=6,Premissas!$B$23,Premissas!$B$24) -> 110 | D16: =B16*Premissas!$B$25 -> 59.130932 | E16: =B16+C16-D16 -> 707.87942 | F16: =E16*Premissas!$B$12 -> 382373.46 | G16: =$F16*Premissas!$B$15 -> 168244.32 | H16: =$F16*Premissas!$B$16 -> 53532.284 | I16: =$F16*Premissas!$B$17 -> 45884.815 | J16: =C16*Premissas!$B$26 -> 15400 | K16: =$F16*Premissas!$B$18 -> 17206.806 | L16: =$F16*Premissas!$B$19 -> 24854.275 | M16: =SUM(G16:L16) -> 325122.5 | N16: =F16-M16 -> 57250.957 | O16: =IFERROR(N16/F16,0) -> 0.14972524 | P16: =P15+N16 -> 337664.88
A17: 13 | B17: =E16 -> 707.87942 | C17: =IF(A17<=6,Premissas!$B$23,Premissas!$B$24) -> 110 | D17: =B17*Premissas!$B$25 -> 63.709148 | E17: =B17+C17-D17 -> 754.17027 | F17: =E17*Premissas!$B$12 -> 407378.27 | G17: =$F17*Premissas!$B$15 -> 179246.44 | H17: =$F17*Premissas!$B$16 -> 57032.958 | I17: =$F17*Premissas!$B$17 -> 48885.392 | J17: =C17*Premissas!$B$26 -> 15400 | K17: =$F17*Premissas!$B$18 -> 18332.022 | L17: =$F17*Premissas!$B$19 -> 26479.588 | M17: =SUM(G17:L17) -> 345376.4 | N17: =F17-M17 -> 62001.871 | O17: =IFERROR(N17/F17,0) -> 0.1521973 | P17: =P16+N17 -> 399666.75
... A28: 24 | B28: =E27 -> 1039.9552 | C28: =IF(A28<=6,Premissas!$B$23,Premissas!$B$24) -> 110 | D28: =B28*Premissas!$B$25 -> 93.595972 | E28: =B28+C28-D28 -> 1056.3593 | F28: =E28*Premissas!$B$12 -> 570610.95 | G28: =$F28*Premissas!$B$15 -> 251068.82 | H28: =$F28*Premissas!$B$16 -> 79885.533 | I28: =$F28*Premissas!$B$17 -> 68473.314 | J28: =C28*Premissas!$B$26 -> 15400 | K28: =$F28*Premissas!$B$18 -> 25677.493 | L28: =$F28*Premissas!$B$19 -> 37089.712 | M28: =SUM(G28:L28) -> 477594.87 | N28: =F28-M28 -> 93016.08 | O28: =IFERROR(N28/F28,0) -> 0.16301138 | P28: =P27+N28 -> 1296506.5
A30: Total Ano 1 (Meses 1-12) | F30: =SUM(F5:F16) -> 2528762.5 | M30: =SUM(M5:M16) -> 2191097.6 | N30: =SUM(N5:N16) -> 337664.88
A31: Total Ano 2 (Meses 13-24) | F31: =SUM(F17:F28) -> 6019166.5 | M31: =SUM(M17:M28) -> 5060324.8 | N31: =SUM(N17:N28) -> 958841.63
A33: 1º mês com EBITDA positivo: | C33: =IFERROR(INDEX(A5:A28,MATCH(TRUE(),INDEX(N5:N28>0,0),0)),"não atingido em 24 meses") -> 1

Sheet Unit Economics
A1: Unit Economics — Praça-piloto
A3: Margem de Contribuição
A4: Margem de contribuição (%) [1 - produto - CD - logística] | B4: =1-Premissas!$B$15-Premissas!$B$16-Premissas!$B$17 -> 0.3 | D4: Exclui tecnologia/admin, tratados como custo mais fixo/overhead nesta análise de unidade
A5: Margem de contribuição por assinante / mês (R$) | B5: =Premissas!$B$12*B4 -> 162.05025
A7: LTV, CAC e Payback
A8: LTV (valor vitalício por assinante, R$) | B8: =B5/Premissas!$B$25 -> 1800.5583 | D8: LTV = margem de contribuição mensal / churn mensal
A9: CAC (R$) | B9: =Premissas!$B$26 -> 140
A10: Razão LTV / CAC | B10: =B8/B9 -> 12.861131 | D10: Referência de mercado: >3x é considerado saudável para negócios de assinatura
A11: Payback do CAC (meses) | B11: =B9/B5 -> 0.86392955
A12: Vida útil média do assinante (meses) | B12: =1/Premissas!$B$25 -> 11.111111
A14: Ponto de Equilíbrio (breakeven)
A15: Custos fixos mensais estimados do CD + time base (R$) | B15: 50000
A16: Assinantes necessários para cobrir custo fixo (breakeven) | B16: =B15/B5 -> 308.54627 | D16: Assinantes ativos = custo fixo mensal / margem de contribuição por assinante

Sheet Investimento Inicial
A1: Investimento Inicial (Pré-operacional) — Praça-piloto
A3: Item | B3: Estimativa mínima (R$) | C3: Estimativa máxima (R$) | D3: Observação
A4: Estruturação do CD (câmara fria, bancadas, balanças, embalagens) | B4: 60000 | C4: 120000 | D4: Depende do tamanho do CD e de comprar vs. alugar equipamento
A5: Veículo(s) refrigerado(s) | B5: 40000 | C5: 90000 | D5: Compra ou entrada de leasing; pode ser reduzido terceirizando 100% no piloto
A6: Site + loja online (setup em plataforma) | B6: 15000 | C6: 35000 | D6: Plataforma pronta (ex.: Shopify + apps de assinatura) recomendada no MVP
A7: App/portal fornecedor + cliente (MVP low-code) | B7: 40000 | C7: 90000 | D7: Evitar desenvolvimento proprietário caro antes de validar retenção
A8: Marca, identidade visual, conteúdo inicial | B8: 15000 | C8: 30000
A9: Licenças, certificações, jurídico/contratos | B9: 10000 | C9: 20000 | D9: Inclui licença sanitária do CD e contratos-padrão com fornecedores
A10: Capital de giro (2-3 ciclos de pagamento a fornecedores) | B10: 60000 | C10: 120000 | D10: Fornecedores pequenos exigem prazo de pagamento curto (seção 4.1 do plano)
A11: Subtotal | B11: =SUM(B4:B10) -> 240000 | C11: =SUM(C4:C10) -> 505000
A12: Reserva de contingência (%) | B12: 0.15
A13: Reserva de contingência (R$) | B13: =B11*B12 -> 36000 | C13: =C11*B12 -> 75750
A14: TOTAL ESTIMADO | B14: =B11+B13 -> 276000 | C14: =C11+C13 -> 580750

Sheet Comparativo de Capitais
A1: Matriz de Decisão — Escolha da Praça-piloto e Ordem de Expansão
A2: Dados brutos vêm da pesquisa de mercado (seção 2.4/2.5 do plano). Pesos e scores de concorrência são premissas editáveis (azul/amarelo).
A4: Pesos dos critérios (devem somar 100%)
A5: Peso: População (tamanho de mercado) | B5: 0.15
A6: Peso: Renda per capita (poder de compra) | B6: 0.2
A7: Peso: Produtores certificados (densidade de fornecimento) | B7: 0.3
A8: Peso: Penetração regional de orgânicos | B8: 0.15
A9: Peso: Ausência de concorrência direta | B9: 0.2
A10: Soma dos pesos (deve ser 100%) | B10: =B5+B6+B7+B8+B9 -> 1
A12: Capital | B12: População (milhões) | C12: Renda per capita do estado (R$) | D12: Produtores certificados (estado) | E12: Penetração regional (%) | F12: Ausência de concorrência (0-1) | G12: Score População | H12: Score Renda | I12: Score Produtores | J12: Score Penetração | K12: Score Concorrência | L12: SCORE PONDERADO | M12: Ranking
A13: Curitiba (PR) | B13: 3.72 | C13: 2762 | D13: 4510 | E13: 0.3 | F13: 1 | G13: =(B13-MIN($B$13:$B$17))/(MAX($B$13:$B$17)-MIN($B$13:$B$17)) -> 0.2142171 | H13: =(C13-MIN($C$13:$C$17))/(MAX($C$13:$C$17)-MIN($C$13:$C$17)) -> 0 | I13: =(D13-MIN($D$13:$D$17))/(MAX($D$13:$D$17)-MIN($D$13:$D$17)) -> 1 | J13: =(E13-MIN($E$13:$E$17))/(MAX($E$13:$E$17)-MIN($E$13:$E$17)) -> 0 | K13: =F13 -> 1 | L13: =G13*$B$5+H13*$B$6+I13*$B$7+J13*$B$8+K13*$B$9 -> 0.53213256 | M13: =RANK(L13,$L$13:$L$17,0) -> 1
A14: Porto Alegre (RS) | B14: 4.17 | C14: 2839 | D14: 3273 | E14: 0.3 | F14: 1 | G14: =(B14-MIN($B$13:$B$17))/(MAX($B$13:$B$17)-MIN($B$13:$B$17)) -> 0.25744476 | H14: =(C14-MIN($C$13:$C$17))/(MAX($C$13:$C$17)-MIN($C$13:$C$17)) -> 0.043355856 | I14: =(D14-MIN($D$13:$D$17))/(MAX($D$13:$D$17)-MIN($D$13:$D$17)) -> 0.65734072 | J14: =(E14-MIN($E$13:$E$17))/(MAX($E$13:$E$17)-MIN($E$13:$E$17)) -> 0 | K14: =F14 -> 1 | L14: =G14*$B$5+H14*$B$6+I14*$B$7+J14*$B$8+K14*$B$9 -> 0.4444901 | M14: =RANK(L14,$L$13:$L$17,0) -> 3
A15: Brasília (DF) | B15: 3 | C15: 4538 | D15: 1200 | E15: 0.42 | F15: 0.3 | G15: =(B15-MIN($B$13:$B$17))/(MAX($B$13:$B$17)-MIN($B$13:$B$17)) -> 0.14505283 | H15: =(C15-MIN($C$13:$C$17))/(MAX($C$13:$C$17)-MIN($C$13:$C$17)) -> 1 | I15: =(D15-MIN($D$13:$D$17))/(MAX($D$13:$D$17)-MIN($D$13:$D$17)) -> 0.083102493 | J15: =(E15-MIN($E$13:$E$17))/(MAX($E$13:$E$17)-MIN($E$13:$E$17)) -> 1 | K15: =F15 -> 0.3 | L15: =G15*$B$5+H15*$B$6+I15*$B$7+J15*$B$8+K15*$B$9 -> 0.45668867 | M15: =RANK(L15,$L$13:$L$17,0) -> 2
A16: São Paulo (SP) | B16: 11.9 | C16: 2956 | D16: 1500 | E16: 0.3 | F16: 0.5 | G16: =(B16-MIN($B$13:$B$17))/(MAX($B$13:$B$17)-MIN($B$13:$B$17)) -> 1 | H16: =(C16-MIN($C$13:$C$17))/(MAX($C$13:$C$17)-MIN($C$13:$C$17)) -> 0.10923423 | I16: =(D16-MIN($D$13:$D$17))/(MAX($D$13:$D$17)-MIN($D$13:$D$17)) -> 0.16620499 | J16: =(E16-MIN($E$13:$E$17))/(MAX($E$13:$E$17)-MIN($E$13:$E$17)) -> 0 | K16: =F16 -> 0.5 | L16: =G16*$B$5+H16*$B$6+I16*$B$7+J16*$B$8+K16*$B$9 -> 0.32170834 | M16: =RANK(L16,$L$13:$L$17,0) -> 4
A17: Florianópolis (SC) | B17: 1.49 | C17: 2809 | D17: 900 | E17: 0.3 | F17: 1 | G17: =(B17-MIN($B$13:$B$17))/(MAX($B$13:$B$17)-MIN($B$13:$B$17)) -> 0 | H17: =(C17-MIN($C$13:$C$17))/(MAX($C$13:$C$17)-MIN($C$13:$C$17)) -> 0.026463964 | I17: =(D17-MIN($D$13:$D$17))/(MAX($D$13:$D$17)-MIN($D$13:$D$17)) -> 0 | J17: =(E17-MIN($E$13:$E$17))/(MAX($E$13:$E$17)-MIN($E$13:$E$17)) -> 0 | K17: =F17 -> 1 | L17: =G17*$B$5+H17*$B$6+I17*$B$7+J17*$B$8+K17*$B$9 -> 0.20529279 | M17: =RANK(L17,$L$13:$L$17,0) -> 5

Sheet Payback e Franquia
A1: Payback do Investimento e Economia de Franquia
A3: Premissas de Franquia
A4: Taxa de franquia inicial (R$) | B4: 60000
A5: Royalty mensal (% da receita bruta) | B5: 0.05
A6: Fundo de marketing (% da receita bruta) | B6: 0.015
A8: Mês | B8: Receita | C8: EBITDA (matriz opera) | D8: EBITDA acum. (matriz opera) | E8: Royalty + Fundo mkt | F8: EBITDA (franqueado) | G8: EBITDA acum. (franqueado)
A9: =A5 -> Royalty mensal (% da receita bruta) | B9: ='Projecao 24 Meses'!F5 -> 56987.671 | C9: ='Projecao 24 Meses'!N5 -> 2427.6575 | D9: ='Projecao 24 Meses'!P5 -> 2427.6575 | E9: =B9*($B$5+$B$6) -> 3704.1986 | F9: =C9-E9 -> -1276.5411 | G9: =F9 -> -1276.5411
A10: =A6 -> Fundo de marketing (% da receita bruta) | B10: ='Projecao 24 Meses'!F6 -> 84268.831 | C10: ='Projecao 24 Meses'!N6 -> 7611.0779 | D10: ='Projecao 24 Meses'!P6 -> 10038.735 | E10: =B10*($B$5+$B$6) -> 5477.474 | F10: =C10-E10 -> 2133.6039 | G10: =G9+F10 -> 857.06276
A11: =A7 -> 0 | B11: ='Projecao 24 Meses'!F7 -> 109094.69 | C11: ='Projecao 24 Meses'!N7 -> 12327.99 | D11: ='Projecao 24 Meses'!P7 -> 22366.726 | E11: =B11*($B$5+$B$6) -> 7091.1546 | F11: =C11-E11 -> 5236.8358 | G11: =G10+F11 -> 6093.8985
A12: =A8 -> Mês | B12: ='Projecao 24 Meses'!F8 -> 131686.21 | C12: ='Projecao 24 Meses'!N8 -> 16620.381 | D12: ='Projecao 24 Meses'!P8 -> 38987.106 | E12: =B12*($B$5+$B$6) -> 8559.6039 | F12: =C12-E12 -> 8060.7768 | G12: =G11+F12 -> 14154.675
A13: =A9 -> Royalty mensal (% da receita bruta) | B13: ='Projecao 24 Meses'!F9 -> 152244.51 | C13: ='Projecao 24 Meses'!N9 -> 20526.456 | D13: ='Projecao 24 Meses'!P9 -> 59513.562 | E13: =B13*($B$5+$B$6) -> 9895.8928 | F13: =C13-E13 -> 10630.563 | G13: =G12+F13 -> 24785.238
A14: =A10 -> Fundo de marketing (% da receita bruta) | B14: ='Projecao 24 Meses'!F10 -> 170952.55 | C14: ='Projecao 24 Meses'!N10 -> 24080.984 | D14: ='Projecao 24 Meses'!P10 -> 83594.547 | E14: =B14*($B$5+$B$6) -> 11111.916 | F14: =C14-E14 -> 12969.069 | G14: =G13+F14 -> 37754.307
A15: =A11 -> 0 | B15: ='Projecao 24 Meses'!F11 -> 214985.25 | C15: ='Projecao 24 Meses'!N11 -> 25447.197 | D15: ='Projecao 24 Meses'!P11 -> 109041.74 | E15: =B15*($B$5+$B$6) -> 13974.041 | F15: =C15-E15 -> 11473.156 | G15: =G14+F15 -> 49227.463
A16: =A12 -> Mês | B16: ='Projecao 24 Meses'!F12 -> 255055 | C16: ='Projecao 24 Meses'!N12 -> 33060.45 | D16: ='Projecao 24 Meses'!P12 -> 142102.19 | E16: =B16*($B$5+$B$6) -> 16578.575 | F16: =C16-E16 -> 16481.875 | G16: =G15+F16 -> 65709.338
A17: =A13 -> Royalty mensal (% da receita bruta) | B17: ='Projecao 24 Meses'!F13 -> 291518.47 | C17: ='Projecao 24 Meses'!N13 -> 39988.51 | D17: ='Projecao 24 Meses'!P13 -> 182090.7 | E17: =B17*($B$5+$B$6) -> 18948.701 | F17: =C17-E17 -> 21039.809 | G17: =G16+F17 -> 86749.147
A18: =A14 -> Fundo de marketing (% da receita bruta) | B18: ='Projecao 24 Meses'!F14 -> 324700.24 | C18: ='Projecao 24 Meses'!N14 -> 46293.045 | D18: ='Projecao 24 Meses'!P14 -> 228383.75 | E18: =B18*($B$5+$B$6) -> 21105.515 | F18: =C18-E18 -> 25187.529 | G18: =G17+F18 -> 111936.68
A19: =A15 -> 0 | B19: ='Projecao 24 Meses'!F15 -> 354895.64 | C19: ='Projecao 24 Meses'!N15 -> 52030.171 | D19: ='Projecao 24 Meses'!P15 -> 280413.92 | E19: =B19*($B$5+$B$6) -> 23068.217 | F19: =C19-E19 -> 28961.955 | G19: =G18+F19 -> 140898.63
A20: =A16 -> Mês | B20: ='Projecao 24 Meses'!F16 -> 382373.46 | C20: ='Projecao 24 Meses'!N16 -> 57250.957 | D20: ='Projecao 24 Meses'!P16 -> 337664.88 | E20: =B20*($B$5+$B$6) -> 24854.275 | F20: =C20-E20 -> 32396.682 | G20: =G19+F20 -> 173295.31
A21: =A17 -> Royalty mensal (% da receita bruta) | B21: ='Projecao 24 Meses'!F17 -> 407378.27 | C21: ='Projecao 24 Meses'!N17 -> 62001.871 | D21: ='Projecao 24 Meses'!P17 -> 399666.75 | E21: =B21*($B$5+$B$6) -> 26479.588 | F21: =C21-E21 -> 35522.284 | G21: =G20+F21 -> 208817.6
... A32: =A28 -> Mês | B32: ='Projecao 24 Meses'!F28 -> 570610.95 | C32: ='Projecao 24 Meses'!N28 -> 93016.08 | D32: ='Projecao 24 Meses'!P28 -> 1296506.5 | E32: =B32*($B$5+$B$6) -> 37089.712 | F32: =C32-E32 -> 55926.369 | G32: =G31+F32 -> 740891.12
A34: Payback do Investimento (interpolado, em meses)
A35: Payback matriz — investimento R$275k (piso) | B35: =IFERROR(MATCH(TRUE(),INDEX(D9:D32>='Investimento Inicial'!$B$14,0),0),"") -> 11 | C35: =IFERROR(B35-1+IFERROR(('Investimento Inicial'!$B$14-(IF(B35=1,0,INDEX(D9:D32,B35-1))))/((INDEX(D9:D32,B35))-(IF(B35=1,0,INDEX(D9:D32,B35-1)))),0),"não atingido em 24 meses") -> 10.915166
A36: Payback matriz — investimento R$580k (teto) | B36: =IFERROR(MATCH(TRUE(),INDEX(D9:D32>='Investimento Inicial'!$C$14,0),0),"") -> 16 | C36: =IFERROR(B36-1+IFERROR(('Investimento Inicial'!$C$14-(IF(B36=1,0,INDEX(D9:D32,B36-1))))/((INDEX(D9:D32,B36))-(IF(B36=1,0,INDEX(D9:D32,B36-1)))),0),"não atingido em 24 meses") -> 15.602639
A37: Payback franqueado — investimento R$275k (piso) | B37: =IFERROR(MATCH(TRUE(),INDEX(G9:G32>='Investimento Inicial'!$B$14,0),0),"") -> 15 | C37: =IFERROR(B37-1+IFERROR(('Investimento Inicial'!$B$14-(IF(B37=1,0,INDEX(G9:G32,B37-1))))/((INDEX(G9:G32,B37))-(IF(B37=1,0,INDEX(G9:G32,B37-1)))),0),"não atingido em 24 meses") -> 14.703599
A38: Payback franqueado — investimento R$580k (teto) | B38: =IFERROR(MATCH(TRUE(),INDEX(G9:G32>='Investimento Inicial'!$C$14,0),0),"") -> 22 | C38: =IFERROR(B38-1+IFERROR(('Investimento Inicial'!$C$14-(IF(B38=1,0,INDEX(G9:G32,B38-1))))/((INDEX(G9:G32,B38))-(IF(B38=1,0,INDEX(G9:G32,B38-1)))),0),"não atingido em 24 meses") -> 21.07846
A40: (Coluna B = mês inteiro em que o acumulado cruza o investimento; Coluna C = payback interpolado, em meses fracionários)
A43: Receita da Franqueadora por Unidade Franqueada
A44: Taxa de franquia inicial (one-off) | B44: =$B$4 -> 60000
A45: Royalty + fundo de marketing no mês 12 (R$/mês) | B45: =E20 -> 24854.275
A46: Royalty + fundo de marketing no mês 24 (R$/mês) | B46: =E32 -> 37089.712
A47: Receita acumulada da franqueadora nos 24 meses (taxa + royalty + fundo) | B47: =$B$4+SUM(E9:E32) -> 615615.38
